<?xml version="1.0" encoding="UTF-8"?>
<!DOCTYPE mapper PUBLIC "-//mybatis.org//DTD Mapper 3.0//EN" "http://mybatis.org/dtd/mybatis-3-mapper.dtd">
<mapper namespace="tw.com.imsoft.dao.mapper.custom.TyOrderDetailMapper">
  <resultMap id="BaseResultMap" type="tw.com.imsoft.dao.model.TyOrderDetail">
    <!--
      WARNING - @mbg.generated
      This element is automatically generated by MyBatis Generator, do not modify.
      This element was generated on Mon Mar 06 15:47:11 CST 2023.
    -->
    <id column="ORDER_DETAIL_NO" jdbcType="NUMERIC" property="orderDetailNo" />
    <result column="ORDER_NO" jdbcType="NUMERIC" property="orderNo" />
    <result column="PRODUCT_ID" jdbcType="NUMERIC" property="productId" />
    <result column="REMARK" jdbcType="VARCHAR" property="remark" />
    <result column="NUM" jdbcType="NUMERIC" property="num" />
    <result column="SUM" jdbcType="NUMERIC" property="sum" />
  </resultMap>
  
</mapper>