<?xml version="1.0" encoding="UTF-8"?>
<!DOCTYPE mapper PUBLIC "-//mybatis.org//DTD Mapper 3.0//EN" "http://mybatis.org/dtd/mybatis-3-mapper.dtd">
<mapper namespace="tw.com.imsoft.dao.mapper.custom.TyOrderCustomMapper">
  <resultMap id="BaseResultMap" type="tw.com.imsoft.dao.model.TyOrder">
    <!--
      WARNING - @mbg.generated
      This element is automatically generated by MyBatis Generator, do not modify.
      This element was generated on Mon Mar 06 15:47:11 CST 2023.
    -->
    <id column="ORDER_NO" jdbcType="NUMERIC" property="orderNo" />
    <result column="MEM_ID" jdbcType="NUMERIC" property="memId" />
    <result column="STORE_ID" jdbcType="NUMERIC" property="storeId" />
    <result column="DISCOUNT" jdbcType="NUMERIC" property="discount" />
    <result column="TOTAL_PRICE" jdbcType="NUMERIC" property="totalPrice" />
    <result column="ORDER_TIME" jdbcType="TIMESTAMP" property="orderTime" />
    <result column="GET_TIME" jdbcType="TIMESTAMP" property="getTime" />
    <result column="STATUS" jdbcType="VARCHAR" property="status" />
  </resultMap>
  
</mapper>